[
  {
    "title": "Mr. Anderson",
    "date": "future",
    "content": "Welcome to the real world"
  },
  {
    "title": "Rorschach",
    "date": "future",
    "content": "I'm not locked up in here with you, you're locked up in here with me!"
  },
  {
    "title": "Trinity",
    "date": "future",
    "content": "I know kung fu."
  },
  {
    "title": "Morpheus",
    "date": "future",
    "content": "I'm going to show you how deep the rabbit hole goes."
  },
  {
    "title": "Agent Smith",
    "date": "future",
    "content": "MIB, you're a dead man."
  }
]
